{
  "region": "us-east-1",
  "instance": "db.z1d.6xlarge",
  "deployment": "multi-az",
  "engine": "oracle",
  "license": null,
  "onDemand": {
    "hourly": 13.79182,
    "daily": 331.00368,
    "sku": "8KMNR5EPC7HSDMTH"
  },
  "savingsOptions": {
    "1yr_Partial Upfront": {
      "term": "1yr",
      "purchaseOption": "Partial Upfront",
      "upfront": 20096.48,
      "hourly": 2.294136,
      "effectiveHourly": 4.586684,
      "daily": 110.080427
    },
    "1yr_All Upfront": {
      "term": "1yr",
      "purchaseOption": "All Upfront",
      "upfront": 39389.72,
      "hourly": 0,
      "effectiveHourly": 4.493466,
      "daily": 107.843176
    },
    "1yr_No Upfront": {
      "term": "1yr",
      "purchaseOption": "No Upfront",
      "upfront": 0,
      "hourly": 4.81772,
      "effectiveHourly": 4.81772,
      "daily": 115.62528
    },
    "3yr_All Upfront": {
      "term": "3yr",
      "purchaseOption": "All Upfront",
      "upfront": 81808.36,
      "hourly": 0,
      "effectiveHourly": 3.11082,
      "daily": 74.659694
    },
    "3yr_Partial Upfront": {
      "term": "3yr",
      "purchaseOption": "Partial Upfront",
      "upfront": 41739.24,
      "hourly": 1.588248,
      "effectiveHourly": 3.175412,
      "daily": 76.209889
    }
  }
}