{
  "region": "us-east-1",
  "instance": "db.t3.large",
  "deployment": "single-az",
  "engine": "aurora-postgresql",
  "license": null,
  "onDemand": {
    "hourly": 0.14104,
    "daily": 3.38496,
    "adjustedAmortisedHourly": 0.14104,
    "adjustedAmortisedDaily": 3.38496,
    "sku": "5EN6FB92Y7XKXFTT"
  },
  "savingsOptions": {
    "1yr_Partial Upfront": {
      "term": "1yr",
      "purchaseOption": "Partial Upfront",
      "upfront": 417.1,
      "hourly": 0.047644,
      "daily": 1.143456,
      "adjustedAmortisedHourly": 0.095225,
      "adjustedAmortisedDaily": 2.285414
    },
    "1yr_No Upfront": {
      "term": "1yr",
      "purchaseOption": "No Upfront",
      "upfront": 0,
      "hourly": 0.11008,
      "daily": 2.64192,
      "adjustedAmortisedHourly": 0.11008,
      "adjustedAmortisedDaily": 2.64192
    },
    "3yr_Partial Upfront": {
      "term": "3yr",
      "purchaseOption": "Partial Upfront",
      "upfront": 882.36,
      "hourly": 0.03354,
      "daily": 0.80496,
      "adjustedAmortisedHourly": 0.067092,
      "adjustedAmortisedDaily": 1.610217
    },
    "3yr_All Upfront": {
      "term": "3yr",
      "purchaseOption": "All Upfront",
      "upfront": 1606.48,
      "hourly": 0,
      "daily": 0,
      "adjustedAmortisedHourly": 0.061088,
      "adjustedAmortisedDaily": 1.4661
    },
    "1yr_All Upfront": {
      "term": "1yr",
      "purchaseOption": "All Upfront",
      "upfront": 818.72,
      "hourly": 0,
      "daily": 0,
      "adjustedAmortisedHourly": 0.093397,
      "adjustedAmortisedDaily": 2.241533
    }
  }
}