{
  "region": "eu-west-1",
  "instance": "db.m5.8xlarge",
  "deployment": "multi-az",
  "engine": "mysql",
  "license": null,
  "onDemand": {
    "hourly": 5.203,
    "daily": 124.872,
    "sku": "M4YTMDKHJ8AHEJ7F"
  },
  "savingsOptions": {
    "1yr_Partial Upfront": {
      "term": "1yr",
      "purchaseOption": "Partial Upfront",
      "upfront": 97614.3,
      "hourly": 11.143192,
      "effectiveHourly": 22.27875,
      "daily": 534.689996
    },
    "1yr_No Upfront": {
      "term": "1yr",
      "purchaseOption": "No Upfront",
      "upfront": 0,
      "hourly": 22.7556,
      "effectiveHourly": 22.7556,
      "daily": 546.1344
    },
    "1yr_All Upfront": {
      "term": "1yr",
      "purchaseOption": "All Upfront",
      "upfront": 191325.06,
      "hourly": 0,
      "effectiveHourly": 21.825811,
      "daily": 523.819466
    },
    "3yr_Partial Upfront": {
      "term": "3yr",
      "purchaseOption": "Partial Upfront",
      "upfront": 31439.02,
      "hourly": 1.19626,
      "effectiveHourly": 2.391751,
      "daily": 57.402022
    },
    "3yr_All Upfront": {
      "term": "3yr",
      "purchaseOption": "All Upfront",
      "upfront": 61619.86,
      "hourly": 0,
      "effectiveHourly": 2.343139,
      "daily": 56.235328
    },
    "3yr_No Upfront": null
  }
}