{
  "region": "us-east-1",
  "instance": "db.r6idn.4xlarge",
  "deployment": "multi-az",
  "engine": "Db2",
  "license": null,
  "onDemand": {
    "hourly": 5.33888,
    "daily": 128.13312,
    "effectiveHourly": 5.33888,
    "effectiveDaily": 128.13312,
    "sku": "3MXKMT92WYC8JUJC"
  },
  "savingsOptions": {
    "1yr_No Upfront": {
      "term": "1yr",
      "purchaseOption": "No Upfront",
      "upfront": 0,
      "hourly": 4.110886,
      "daily": 98.661264,
      "effectiveHourly": 4.110886,
      "effectiveDaily": 98.661264
    },
    "1yr_Partial Upfront": {
      "term": "1yr",
      "purchaseOption": "Partial Upfront",
      "upfront": 17538.22,
      "hourly": 2.00208,
      "daily": 48.04992,
      "effectiveHourly": 4.00279,
      "effectiveDaily": 96.066952
    },
    "3yr_All Upfront": {
      "term": "3yr",
      "purchaseOption": "All Upfront",
      "upfront": 74362.06,
      "hourly": 0,
      "daily": 0,
      "effectiveHourly": 2.82767,
      "effectiveDaily": 67.864073
    },
    "1yr_All Upfront": {
      "term": "1yr",
      "purchaseOption": "All Upfront",
      "upfront": 34141.07,
      "hourly": 0,
      "daily": 0,
      "effectiveHourly": 3.894715,
      "effectiveDaily": 93.473158
    },
    "3yr_Partial Upfront": {
      "term": "3yr",
      "purchaseOption": "Partial Upfront",
      "upfront": 38584.09,
      "hourly": 1.468192,
      "daily": 35.236608,
      "effectiveHourly": 2.93538,
      "effectiveDaily": 70.449101
    }
  }
}