{
  "region": "us-east-1",
  "instance": "db.r5b.8xlarge",
  "deployment": "multi-az",
  "engine": "oracle-ee-byol",
  "license": "byol",
  "onDemand": {
    "hourly": 7.58606,
    "daily": 182.06544,
    "adjustedAmortisedHourly": 7.58606,
    "adjustedAmortisedDaily": 182.06544,
    "sku": "BXZWJREAVF2BNANC"
  },
  "savingsOptions": {
    "3yr_All Upfront": {
      "term": "3yr",
      "purchaseOption": "All Upfront",
      "upfront": 78148.2,
      "hourly": 0,
      "daily": 0,
      "adjustedAmortisedHourly": 2.971641,
      "adjustedAmortisedDaily": 71.31937
    },
    "3yr_Partial Upfront": {
      "term": "3yr",
      "purchaseOption": "Partial Upfront",
      "upfront": 39871.32,
      "hourly": 1.517212,
      "daily": 36.413088,
      "adjustedAmortisedHourly": 3.033347,
      "adjustedAmortisedDaily": 72.80033
    },
    "1yr_All Upfront": {
      "term": "1yr",
      "purchaseOption": "All Upfront",
      "upfront": 39074.1,
      "hourly": 0,
      "daily": 0,
      "adjustedAmortisedHourly": 4.457461,
      "adjustedAmortisedDaily": 106.979056
    },
    "1yr_Partial Upfront": {
      "term": "1yr",
      "purchaseOption": "Partial Upfront",
      "upfront": 19935.66,
      "hourly": 2.275732,
      "daily": 54.617568,
      "adjustedAmortisedHourly": 4.549935,
      "adjustedAmortisedDaily": 109.19843
    },
    "1yr_No Upfront": {
      "term": "1yr",
      "purchaseOption": "No Upfront",
      "upfront": 0,
      "hourly": 4.779106,
      "daily": 114.698544,
      "adjustedAmortisedHourly": 4.779106,
      "adjustedAmortisedDaily": 114.698544
    }
  }
}