{
  "region": "eu-west-1",
  "instance": "db.t4g.xlarge",
  "deployment": "single-az",
  "engine": "mysql",
  "license": null,
  "onDemand": {
    "hourly": 0.23822,
    "daily": 5.71728,
    "effectiveHourly": 0.23822,
    "effectiveDaily": 5.71728,
    "sku": "3PA24YW98X66XRBB"
  },
  "savingsOptions": {
    "1yr_Partial Upfront": {
      "term": "1yr",
      "purchaseOption": "Partial Upfront",
      "upfront": 657.04,
      "hourly": 0.074992,
      "daily": 1.799808,
      "effectiveHourly": 0.149945,
      "effectiveDaily": 3.598685
    },
    "3yr_Partial Upfront": {
      "term": "3yr",
      "purchaseOption": "Partial Upfront",
      "upfront": 1376,
      "hourly": 0.052374,
      "daily": 1.256976,
      "effectiveHourly": 0.104697,
      "effectiveDaily": 2.512737
    },
    "3yr_All Upfront": {
      "term": "3yr",
      "purchaseOption": "All Upfront",
      "upfront": 2690.08,
      "hourly": 0,
      "daily": 0,
      "effectiveHourly": 0.102292,
      "effectiveDaily": 2.455013
    },
    "1yr_All Upfront": {
      "term": "1yr",
      "purchaseOption": "All Upfront",
      "upfront": 1292.58,
      "hourly": 0,
      "daily": 0,
      "effectiveHourly": 0.147454,
      "effectiveDaily": 3.538891
    },
    "1yr_No Upfront": {
      "term": "1yr",
      "purchaseOption": "No Upfront",
      "upfront": 0,
      "hourly": 0.157122,
      "daily": 3.770928,
      "effectiveHourly": 0.157122,
      "effectiveDaily": 3.770928
    }
  }
}