{
  "region": "eu-west-1",
  "instance": "db.x2g.16xlarge",
  "deployment": "single-az",
  "engine": "aurora-mysql",
  "license": null,
  "onDemand": {
    "hourly": 15.8842,
    "daily": 381.2208,
    "effectiveHourly": 15.8842,
    "effectiveDaily": 381.2208,
    "sku": "RKG3ZAKWBVHJEZ2H"
  },
  "savingsOptions": {
    "1yr_All Upfront": {
      "term": "1yr",
      "purchaseOption": "All Upfront",
      "upfront": 58411.2,
      "hourly": 0,
      "daily": 0,
      "effectiveHourly": 6.663381,
      "effectiveDaily": 159.921149
    },
    "1yr_Partial Upfront": {
      "term": "1yr",
      "purchaseOption": "Partial Upfront",
      "upfront": 29676.88,
      "hourly": 3.387798,
      "daily": 81.307152,
      "effectiveHourly": 6.773251,
      "effectiveDaily": 162.558021
    },
    "3yr_All Upfront": {
      "term": "3yr",
      "purchaseOption": "All Upfront",
      "upfront": 118707.52,
      "hourly": 0,
      "daily": 0,
      "effectiveHourly": 4.513937,
      "effectiveDaily": 108.334492
    },
    "1yr_No Upfront": {
      "term": "1yr",
      "purchaseOption": "No Upfront",
      "upfront": 0,
      "hourly": 7.098182,
      "daily": 170.356368,
      "effectiveHourly": 7.098182,
      "effectiveDaily": 170.356368
    },
    "3yr_Partial Upfront": {
      "term": "3yr",
      "purchaseOption": "Partial Upfront",
      "upfront": 60766.74,
      "hourly": 2.312282,
      "daily": 55.494768,
      "effectiveHourly": 4.62298,
      "effectiveDaily": 110.951524
    }
  }
}