{
  "region": "us-east-1",
  "instance": "db.r6i.xlarge",
  "deployment": "multi-az",
  "engine": "sqlserver-web-li",
  "license": "li",
  "onDemand": {
    "hourly": 1.455464,
    "daily": 34.931136,
    "effectiveHourly": 1.455464,
    "effectiveDaily": 34.931136,
    "sku": "9UEU67Y6RVSQXPD9"
  },
  "savingsOptions": {
    "1yr_Partial Upfront": {
      "term": "1yr",
      "purchaseOption": "Partial Upfront",
      "upfront": 1988.32,
      "hourly": 0.22704,
      "daily": 5.44896,
      "effectiveHourly": 0.453862,
      "effectiveDaily": 10.892683
    },
    "1yr_All Upfront": {
      "term": "1yr",
      "purchaseOption": "All Upfront",
      "upfront": 3897.52,
      "hourly": 0,
      "daily": 0,
      "effectiveHourly": 0.444617,
      "effectiveDaily": 10.670828
    },
    "1yr_No Upfront": {
      "term": "1yr",
      "purchaseOption": "No Upfront",
      "upfront": 0,
      "hourly": 0.476784,
      "daily": 11.442816,
      "effectiveHourly": 0.476784,
      "effectiveDaily": 11.442816
    },
    "3yr_Partial Upfront": {
      "term": "3yr",
      "purchaseOption": "Partial Upfront",
      "upfront": 4014.48,
      "hourly": 0.152736,
      "daily": 3.665664,
      "effectiveHourly": 0.305389,
      "effectiveDaily": 7.329347
    },
    "3yr_All Upfront": {
      "term": "3yr",
      "purchaseOption": "All Upfront",
      "upfront": 7867.28,
      "hourly": 0,
      "daily": 0,
      "effectiveHourly": 0.299159,
      "effectiveDaily": 7.179813
    }
  }
}