{
  "region": "eu-west-1",
  "instance": "db.r6idn.2xlarge",
  "deployment": "single-az",
  "engine": "postgresql",
  "license": null,
  "onDemand": {
    "hourly": 1.48694,
    "daily": 35.68656,
    "effectiveHourly": 1.48694,
    "effectiveDaily": 35.68656,
    "sku": "VU8DKVKQHFCWDN56"
  },
  "savingsOptions": {
    "3yr_Partial Upfront": {
      "term": "3yr",
      "purchaseOption": "Partial Upfront",
      "upfront": 10739.9,
      "hourly": 0.408672,
      "daily": 9.808128,
      "effectiveHourly": 0.817064,
      "effectiveDaily": 19.609545
    },
    "3yr_All Upfront": {
      "term": "3yr",
      "purchaseOption": "All Upfront",
      "upfront": 20698.72,
      "hourly": 0,
      "daily": 0,
      "effectiveHourly": 0.787083,
      "effectiveDaily": 18.890003
    },
    "1yr_All Upfront": {
      "term": "1yr",
      "purchaseOption": "All Upfront",
      "upfront": 9503.18,
      "hourly": 0,
      "daily": 0,
      "effectiveHourly": 1.084095,
      "effectiveDaily": 26.01829
    },
    "1yr_Partial Upfront": {
      "term": "1yr",
      "purchaseOption": "Partial Upfront",
      "upfront": 4881.77,
      "hourly": 0.55728,
      "daily": 13.37472,
      "effectiveHourly": 1.114178,
      "effectiveDaily": 26.740285
    },
    "1yr_No Upfront": {
      "term": "1yr",
      "purchaseOption": "No Upfront",
      "upfront": 0,
      "hourly": 1.14423,
      "daily": 27.46152,
      "effectiveHourly": 1.14423,
      "effectiveDaily": 27.46152
    }
  }
}