{
  "region": "us-east-1",
  "instance": "db.m6idn.12xlarge",
  "deployment": "single-az",
  "engine": "mariadb",
  "license": null,
  "onDemand": {
    "hourly": 6.0888,
    "daily": 146.1312,
    "effectiveHourly": 6.0888,
    "effectiveDaily": 146.1312,
    "sku": "K9BJR7HKWRMGVXKX"
  },
  "savingsOptions": {
    "3yr_Partial Upfront": {
      "term": "3yr",
      "purchaseOption": "Partial Upfront",
      "upfront": 44003.76,
      "hourly": 1.67442,
      "daily": 40.18608,
      "effectiveHourly": 3.347694,
      "effectiveDaily": 80.344654
    },
    "3yr_All Upfront": {
      "term": "3yr",
      "purchaseOption": "All Upfront",
      "upfront": 84807.24,
      "hourly": 0,
      "daily": 0,
      "effectiveHourly": 3.224856,
      "effectiveDaily": 77.396523
    },
    "1yr_No Upfront": {
      "term": "1yr",
      "purchaseOption": "No Upfront",
      "upfront": 0,
      "hourly": 4.688376,
      "daily": 112.521024,
      "effectiveHourly": 4.688376,
      "effectiveDaily": 112.521024
    },
    "1yr_Partial Upfront": {
      "term": "1yr",
      "purchaseOption": "Partial Upfront",
      "upfront": 20001.71,
      "hourly": 2.2833,
      "daily": 54.7992,
      "effectiveHourly": 4.565037,
      "effectiveDaily": 109.560892
    },
    "1yr_All Upfront": {
      "term": "1yr",
      "purchaseOption": "All Upfront",
      "upfront": 38936.65,
      "hourly": 0,
      "daily": 0,
      "effectiveHourly": 4.441781,
      "effectiveDaily": 106.602751
    }
  }
}